aws_inventory/__init__.py
aws_inventory/auth.py
aws_inventory/cli.py
aws_inventory/collector.py
aws_inventory/formatter.py
aws_inventory/collectors/__init__.py
aws_inventory/collectors/accessanalyzer.py
aws_inventory/collectors/acm.py
aws_inventory/collectors/acm_pca.py
aws_inventory/collectors/amp.py
aws_inventory/collectors/amplify.py
aws_inventory/collectors/apigateway.py
aws_inventory/collectors/apigatewayv2.py
aws_inventory/collectors/appconfig.py
aws_inventory/collectors/appflow.py
aws_inventory/collectors/applicationautoscaling.py
aws_inventory/collectors/apprunner.py
aws_inventory/collectors/appsync.py
aws_inventory/collectors/athena.py
aws_inventory/collectors/auditmanager.py
aws_inventory/collectors/autoscaling.py
aws_inventory/collectors/backup.py
aws_inventory/collectors/batch.py
aws_inventory/collectors/bedrock.py
aws_inventory/collectors/budgets.py
aws_inventory/collectors/ce.py
aws_inventory/collectors/cleanrooms.py
aws_inventory/collectors/cloudformation.py
aws_inventory/collectors/cloudfront.py
aws_inventory/collectors/cloudhsmv2.py
aws_inventory/collectors/cloudtrail.py
aws_inventory/collectors/cloudwatch.py
aws_inventory/collectors/codeartifact.py
aws_inventory/collectors/codebuild.py
aws_inventory/collectors/codedeploy.py
aws_inventory/collectors/codepipeline.py
aws_inventory/collectors/cognito.py
aws_inventory/collectors/comprehend.py
aws_inventory/collectors/computeoptimizer.py
aws_inventory/collectors/config.py
aws_inventory/collectors/connect.py
aws_inventory/collectors/datasync.py
aws_inventory/collectors/dax.py
aws_inventory/collectors/detective.py
aws_inventory/collectors/devicefarm.py
aws_inventory/collectors/directconnect.py
aws_inventory/collectors/dlm.py
aws_inventory/collectors/dms.py
aws_inventory/collectors/docdb.py
aws_inventory/collectors/ds.py
aws_inventory/collectors/dynamodb.py
aws_inventory/collectors/ec2.py
aws_inventory/collectors/ecr.py
aws_inventory/collectors/ecr_public.py
aws_inventory/collectors/ecs.py
awsmap-1.1.0.dist-info/licenses/LICENSE
awsmap-1.1.0.dist-info/METADATA
awsmap-1.1.0.dist-info/WHEEL
awsmap-1.1.0.dist-info/entry_points.txt
awsmap-1.1.0.dist-info/top_level.txt
awsmap-1.1.0.dist-info/RECORD
