Metadata-Version: 2.4
Name: awsmap
Version: 1.1.0
Summary: A fast, comprehensive tool for mapping and inventorying AWS resources across 140+ services and all regions
Author-email: Tarek CHEIKH <tarek@tocconsulting.fr>
License: MIT
Project-URL: Homepage, https://github.com/TocConsulting/awsmap
Project-URL: Repository, https://github.com/TocConsulting/awsmap
Project-URL: Issues, https://github.com/TocConsulting/awsmap/issues
Project-URL: Documentation, https://github.com/TocConsulting/awsmap#readme
Keywords: aws,inventory,cloud,infrastructure,devops,boto3,aws-resources,multi-region
Classifier: Development Status :: 5 - Production/Stable
Classifier: Intended Audience :: Developers
Classifier: Intended Audience :: System Administrators
Classifier: License :: OSI Approved :: MIT License
Classifier: Operating System :: OS Independent
Classifier: Programming Language :: Python :: 3
Classifier: Programming Language :: Python :: 3.8
Classifier: Programming Language :: Python :: 3.9
Classifier: Programming Language :: Python :: 3.10
Classifier: Programming Language :: Python :: 3.11
Classifier: Programming Language :: Python :: 3.12
Classifier: Topic :: System :: Systems Administration
Classifier: Topic :: Utilities
Requires-Python: >=3.8
License-File: LICENSE
Requires-Dist: boto3>=1.26.0
Requires-Dist: click>=8.0.0
Requires-Dist: pyyaml>=6.0.0
Provides-Extra: dev
Requires-Dist: pytest>=7.0.0; extra == "dev"
Requires-Dist: pytest-cov>=4.0.0; extra == "dev"
Requires-Dist: moto[dynamodb,ec2,iam,lambda,s3]>=4.0.0; extra == "dev"
Requires-Dist: black>=23.0.0; extra == "dev"
Requires-Dist: isort>=5.0.0; extra == "dev"
Requires-Dist: flake8>=6.0.0; extra == "dev"
Requires-Dist: mypy>=1.0.0; extra == "dev"
Dynamic: license-file
